worldvocoder/__init__.py
worldvocoder/cheaptrick.py
worldvocoder/d4c.py
worldvocoder/d4cRequiem.py
worldvocoder/dio.py
worldvocoder/get_seeds_signals.py
worldvocoder/harvest.py
worldvocoder/main.py
worldvocoder/stonemask.py
worldvocoder/swipe.py
worldvocoder/synthesis.py
worldvocoder/synthesisRequiem.py
worldvocoder/synthesis_a.py
worldvocoder-0.0.5.dist-info/LICENSE.txt
worldvocoder-0.0.5.dist-info/METADATA
worldvocoder-0.0.5.dist-info/WHEEL
worldvocoder-0.0.5.dist-info/top_level.txt
worldvocoder-0.0.5.dist-info/RECORD
