Metadata-Version: 2.1
Name: worldvocoder
Version: 0.0.5
Summary: Python implementation of WORLD vocoder.
Home-page: https://github.com/javanasse/Python-WORLD
Download-URL: https://github.com/javanasse/Python-WORLD/archive/refs/tags/v0.tar.gz
Author: JulianArmandVanasse
Author-email: Julian <julian.vanasse@gmail.com>
Project-URL: Homepage, https://github.com/javanasse/worldvocoder
Classifier: Programming Language :: Python :: 3
Classifier: License :: OSI Approved :: MIT License
Classifier: Operating System :: OS Independent
Requires-Python: >=3.7
License-File: LICENSE.txt
